touch_android-0.1.0.dist-info/LICENSE
touch_android-0.1.0.dist-info/METADATA
touch_android-0.1.0.dist-info/RECORD
touch_android-0.1.0.dist-info/WHEEL
touch_android/__init__.pyc
touch_android/__init__.pyi
touch_android/comm/__init__.pyc
touch_android/comm/__init__.pyi
touch_android/comm/proto/__init__.pyc
touch_android/comm/proto/__init__.pyi
touch_android/comm/proto/touchRP_pb2.pyc
touch_android/comm/proto/touchRP_pb2.pyi
touch_android/comm/proto/touchRP_pb2_grpc.pyc
touch_android/comm/proto/touchRP_pb2_grpc.pyi
touch_android/comm/proxy/ProxyGRPC.pyc
touch_android/comm/proxy/ProxyGRPC.pyi
touch_android/comm/proxy/SVCConsumer.pyc
touch_android/comm/proxy/SVCConsumer.pyi
touch_android/comm/proxy/__init__.pyc
touch_android/comm/proxy/__init__.pyi
touch_android/comm/proxy/service/StatusCum.pyc
touch_android/comm/proxy/service/StatusCum.pyi
touch_android/comm/proxy/service/__init__.pyc
touch_android/comm/proxy/service/__init__.pyi
touch_android/comm/stub/SVCProvider.pyc
touch_android/comm/stub/SVCProvider.pyi
touch_android/comm/stub/StubGRPC.pyc
touch_android/comm/stub/StubGRPC.pyi
touch_android/comm/stub/__init__.pyc
touch_android/comm/stub/__init__.pyi
touch_android/comm/stub/service/StatusPvd.pyc
touch_android/comm/stub/service/StatusPvd.pyi
touch_android/comm/stub/service/__init__.pyc
touch_android/comm/stub/service/__init__.pyi
touch_android/data/CStatus.pyc
touch_android/data/CStatus.pyi
touch_android/data/EnumDefine.pyc
touch_android/data/EnumDefine.pyi
touch_android/data/__init__.pyc
touch_android/data/__init__.pyi
touch_android/policy/POLICY.pyc
touch_android/policy/POLICY.pyi
touch_android/policy/__init__.pyc
touch_android/policy/__init__.pyi
touch_android/recorder/CParseEvt.pyc
touch_android/recorder/CParseEvt.pyi
touch_android/recorder/CSummaryEvt.pyc
touch_android/recorder/CSummaryEvt.pyi
touch_android/recorder/CTProperty.pyc
touch_android/recorder/CTProperty.pyi
touch_android/recorder/CTRecorder.pyc
touch_android/recorder/CTRecorder.pyi
touch_android/recorder/__init__.pyc
touch_android/recorder/__init__.pyi
touch_android/tc_maker/CMakeTC.pyc
touch_android/tc_maker/CMakeTC.pyi
